load/__init__.py
load/load_remote.py
load_remote-2.2.dist-info/METADATA
load_remote-2.2.dist-info/WHEEL
load_remote-2.2.dist-info/top_level.txt
load_remote-2.2.dist-info/RECORD
