Metadata-Version: 2.1
Name: load-remote
Version: 2.2
Summary: load_remote
Home-page: UNKNOWN
Author: huangbo
Author-email: huangbo1990@126.com
License: MIT
Platform: UNKNOWN
